orbital/__init__.py
orbital/ast.py
orbital/sql.py
orbital/translate.py
orbital/types.py
orbital/_utils/__init__.py
orbital/_utils/onnx.py
orbital/_utils/repr_pipeline.py
orbital/translation/__init__.py
orbital/translation/optimizer.py
orbital/translation/options.py
orbital/translation/transformations.py
orbital/translation/translator.py
orbital/translation/variables.py
orbital/translation/steps/__init__.py
orbital/translation/steps/add.py
orbital/translation/steps/argmax.py
orbital/translation/steps/arrayfeatureextractor.py
orbital/translation/steps/cast.py
orbital/translation/steps/concat.py
orbital/translation/steps/div.py
orbital/translation/steps/gather.py
orbital/translation/steps/identity.py
orbital/translation/steps/imputer.py
orbital/translation/steps/labelencoder.py
orbital/translation/steps/linearclass.py
orbital/translation/steps/linearreg.py
orbital/translation/steps/matmul.py
orbital/translation/steps/mul.py
orbital/translation/steps/onehotencoder.py
orbital/translation/steps/reshape.py
orbital/translation/steps/scaler.py
orbital/translation/steps/softmax.py
orbital/translation/steps/sub.py
orbital/translation/steps/where.py
orbital/translation/steps/zipmap.py
orbital/translation/steps/trees/__init__.py
orbital/translation/steps/trees/classifier.py
orbital/translation/steps/trees/regressor.py
orbital/translation/steps/trees/tree.py
orbital-0.3.0.dist-info/licenses/LICENSE.md
orbital-0.3.0.dist-info/METADATA
orbital-0.3.0.dist-info/WHEEL
orbital-0.3.0.dist-info/top_level.txt
orbital-0.3.0.dist-info/RECORD
