Metadata-Version: 2.4
Name: orbital
Version: 0.3.0
Summary: Allow SKLearn predictions to run on database systems in pure SQL.
Author: Posit Software PBC
Author-email: Alessandro Molina <alessandro.molina@posit.co>
License-Expression: MIT
Keywords: database,machine learning,sql
Classifier: Operating System :: Microsoft :: Windows
Classifier: Operating System :: POSIX
Classifier: Operating System :: Unix
Classifier: Operating System :: MacOS
Classifier: Programming Language :: Python :: 3
Classifier: Programming Language :: Python :: 3.9
Classifier: Programming Language :: Python :: 3.10
Classifier: Programming Language :: Python :: 3.11
Classifier: Programming Language :: Python :: 3.12
Classifier: Programming Language :: Python :: 3.13
Classifier: Intended Audience :: Science/Research
Classifier: Intended Audience :: Developers
Classifier: Topic :: Software Development
Classifier: Topic :: Scientific/Engineering
Classifier: Topic :: Database
Classifier: Programming Language :: Python
Classifier: Programming Language :: SQL
Requires-Python: >=3.9
License-File: LICENSE.md
Requires-Dist: packaging
Requires-Dist: scikit-learn
Requires-Dist: skl2onnx~=1.19.1
Requires-Dist: onnx~=1.18.0
Requires-Dist: ibis-framework<11.0.0
Provides-Extra: test
Requires-Dist: pandas; extra == "test"
Requires-Dist: polars-lts-cpu; extra == "test"
Requires-Dist: pyarrow>=19.0.1; extra == "test"
Requires-Dist: pyarrow-hotfix; extra == "test"
Requires-Dist: ibis-framework[duckdb]>=5.1.0; extra == "test"
Requires-Dist: pytest-cov>=5.0.0; extra == "test"
Requires-Dist: pytest>=8.3.2; extra == "test"
Requires-Dist: sqlalchemy; extra == "test"
Requires-Dist: psycopg2-binary; extra == "test"
Requires-Dist: duckdb<1.4.0; extra == "test"
Dynamic: license-file
